EmmaMatiCalPackage/__init__.py
EmmaMatiCalPackage/add.py
EmmaMatiCalPackage/subtract.py
EmmaMatiCalPackage/extras/__init__.py
EmmaMatiCalPackage/extras/divide.py
EmmaMatiCalPackage/extras/multiply.py
EmmaMatiCalPackage/extras/power.py
EmmaMatiCalPackage-0.0.4.dist-info/METADATA
EmmaMatiCalPackage-0.0.4.dist-info/WHEEL
EmmaMatiCalPackage-0.0.4.dist-info/top_level.txt
EmmaMatiCalPackage-0.0.4.dist-info/RECORD
