Metadata-Version: 2.1
Name: EmmaMatiCalPackage
Version: 0.0.4
Summary: My first Python package but the second version
Home-page: UNKNOWN
Author: Emma Hall
Author-email: <elohall01@gmail.com>
License: UNKNOWN
Keywords: python,simpleCalpackage
Platform: UNKNOWN
Classifier: Development Status :: 3 - Alpha
Classifier: Intended Audience :: Education
Classifier: Programming Language :: Python :: 2
Classifier: Programming Language :: Python :: 3
Classifier: Operating System :: MacOS :: MacOS X
Classifier: Operating System :: Microsoft :: Windows
